s2cholar/__init__.py
s2cholar/api_client.py
s2cholar/configuration.py
s2cholar/rest.py
s2cholar/api/__init__.py
s2cholar/api/author_api.py
s2cholar/api/paper_api.py
s2cholar/models/__init__.py
s2cholar/models/author.py
s2cholar/models/author_batch.py
s2cholar/models/author_info.py
s2cholar/models/author_with_papers.py
s2cholar/models/base_paper.py
s2cholar/models/citation.py
s2cholar/models/citation_batch.py
s2cholar/models/citation_citing_paper.py
s2cholar/models/embedding.py
s2cholar/models/error400.py
s2cholar/models/error404.py
s2cholar/models/full_paper.py
s2cholar/models/paper_batch.py
s2cholar/models/paper_info.py
s2cholar/models/paper_search_batch.py
s2cholar/models/paper_with_links.py
s2cholar/models/reference.py
s2cholar/models/reference_batch.py
s2cholar/models/reference_cited_paper.py
test/__init__.py
test/conftest.py
test/test_author_api.py
test/test_paper_api.py
s2cholar-0.1.1.dist-info/LICENSE
s2cholar-0.1.1.dist-info/METADATA
s2cholar-0.1.1.dist-info/WHEEL
s2cholar-0.1.1.dist-info/top_level.txt
s2cholar-0.1.1.dist-info/RECORD
