Metadata-Version: 2.1
Name: s2cholar
Version: 0.1.1
Summary: Python API client for Semantic Scholar
Home-page: https://github.com/luizvbo/s2cholar
Author: Luiz Otavio Vilas Boas Oliveira
Author-email: luiz.vbo@gmail.com
License: MIT license
Keywords: Swagger,Literature Graph Service
Platform: any
Classifier: Development Status :: 2 - Pre-Alpha
Classifier: Intended Audience :: Developers
Classifier: License :: OSI Approved :: MIT License
Classifier: Natural Language :: English
Classifier: Programming Language :: Python :: 3
Classifier: Programming Language :: Python :: 3.6
Classifier: Programming Language :: Python :: 3.7
Classifier: Programming Language :: Python :: 3.8
Classifier: Programming Language :: Python :: 2.7
License-File: LICENSE
Requires-Dist: certifi (>=2017.4.17)
Requires-Dist: python-dateutil (>=2.1)
Requires-Dist: six (>=1.10)
Requires-Dist: urllib3 (>=1.23)
